[{"pk": 1, "model": "pghmarks.landmark", "fields": {"height": 526, "neighborhood": 1, "name": "Cathedral of Learning", "slug": "cathedral-of-learning"}}, {"pk": 3, "model": "pghmarks.landmark", "fields": {"height": 150, "neighborhood": 1, "name": "UPMC Presbyterian", "slug": "upmc-presbyterian"}}, {"pk": 4, "model": "pghmarks.landmark", "fields": {"height": null, "neighborhood": 2, "name": "Market Square", "slug": "market-square"}}, {"pk": 5, "model": "pghmarks.landmark", "fields": {"height": null, "neighborhood": 3, "name": "PNC Park", "slug": "pnc-park"}}, {"pk": 6, "model": "pghmarks.landmark", "fields": {"height": null, "neighborhood": 3, "name": "Heinz Field", "slug": "heinz-field"}}, {"pk": 1, "model": "pghmarks.neighborhood", "fields": {"name": "Oakland"}}, {"pk": 2, "model": "pghmarks.neighborhood", "fields": {"name": "Downtown"}}, {"pk": 3, "model": "pghmarks.neighborhood", "fields": {"name": "North Shore"}}]